<?xml version="1.0" encoding="UTF-8" ?><data>	<answers>		<gridItem answer="Avalanche" />		<gridItem answer="Steeplechase" />		<gridItem answer="Valhalla" />		<gridItem answer="Grand National" />		<modelAnswer>Rides at Blackpool Pleasure Beach</modelAnswer>		<list1>BLACKPOOL,PLEASURE,THEME,ROLLER*</list1>		<list2></list2>	</answers>	<answers>		<gridItem answer="Airport" />		<gridItem answer="Outbreak" />		<gridItem answer="Titanic" />		<gridItem answer="Knowing" />		<modelAnswer>Disaster movies</modelAnswer>		<list1>DISASTER,CALAMITY,CATASTRO*,TRAGED*,</list1>		<list2></list2>	</answers>	<answers>		<gridItem answer="Daylight" />		<gridItem answer="Armed" />		<gridItem answer="Highway" />		<gridItem answer="Bank" />		<modelAnswer>____ robbery</modelAnswer>		<list1>ROBBERY</list1>		<list2></list2>	</answers>	<answers>		<gridItem answer="Elysium" />		<gridItem answer="Limbo" />		<gridItem answer="Duat" />		<gridItem answer="Naraka" />		<modelAnswer>Places in the afterlife</modelAnswer>		<list1>AFTERLIFE,HEAVEN,HELL,HEREAFTER,ETERN*,IMMORTAL,DEATH,DIE*,DECEASE*</list1>		<list2></list2>	</answers></data>