<?xml version="1.0" encoding="UTF-8" ?><data>	<answers>		<gridItem answer="Rafter" />		<gridItem answer="Phoenix" />		<gridItem answer="Eddery" />		<gridItem answer="Garrett" />		<modelAnswer>Famous people called Pat</modelAnswer>		<list1>PAT,PATS</list1>		<list2></list2>	</answers>	<answers>		<gridItem answer="Valley" />		<gridItem answer="Shingles" />		<gridItem answer="Joist" />		<gridItem answer="Ridge" />		<modelAnswer>Parts of a roof</modelAnswer>		<list1>ROOF,ROOVES,CEILING,TOP</list1>		<list2></list2>	</answers>	<answers>		<gridItem answer="Impetigo" />		<gridItem answer="Varicella" />		<gridItem answer="Vitiligo" />		<gridItem answer="Scabies" />		<modelAnswer>Skin problems</modelAnswer>		<list1>SKIN,DISEASE*,INFECTION*,DISORDER*,PROBLEM*</list1>		<list2></list2>	</answers>	<answers>		<gridItem answer="Jennings" />		<gridItem answer="Bunter" />		<gridItem answer="Potter" />		<gridItem answer="Piggy" />		<modelAnswer>Famous schoolboys in literature</modelAnswer>		<list1>SCHOOL*,PUPIL*,BOY*,STUDENT*</list1>		<list2></list2>	</answers></data>